argreq/__init__.py
argreq/errors.py
argreq-0.2.0.dist-info/LICENSE
argreq-0.2.0.dist-info/METADATA
argreq-0.2.0.dist-info/WHEEL
argreq-0.2.0.dist-info/top_level.txt
argreq-0.2.0.dist-info/RECORD
