Metadata-Version: 2.1
Name: argreq
Version: 0.2.0
Summary: Add requirements to function arguments using simple and elegant decorators
Home-page: https://github.com/AvivAbramovich/argreq
Author: Aviv Abramovich
Author-email: AvivAbramovich@gmail.com
License: UNKNOWN
Project-URL: Bug Tracker, https://github.com/AvivAbramovich/argrew/issues
Platform: UNKNOWN
